{"date": "20130921", "stories": [{"image_hue": "0x442823", "title": "\u76f2\u4eba\u7684\u68a6\uff0c\u662f\u4ec0\u4e48\u989c\u8272\u4ec0\u4e48\u5f62\u72b6\u7684", "url": "https://daily.zhihu.com/story/1083636", "hint": "\u6bb7\u6653\u6ce2 \u00b7 1 \u5206\u949f\u9605\u8bfb", "ga_prefix": "092122", "images": ["http://p1.zhimg.com/8a/0c/8a0c90bfec8f56edea9ca64ef356bef1.jpg"], "type": 0, "id": 1083636}, {"image_hue": "0xb3947d", "title": "\u5404\u79cd\u5947\u6280\u6deb\u5de7\u7684\u6a21\u5177\uff0c\u9020\u5c31\u4e86\u7a00\u5947\u53e4\u602a\u7684\u610f\u5927\u5229\u9762", "url": "https://daily.zhihu.com/story/1085025", "hint": "cOMMANDO \u00b7 1 \u5206\u949f\u9605\u8bfb", "ga_prefix": "092121", "images": ["http://p3.zhimg.com/63/37/6337d70565ce7e703af29bf6f3fd9170.jpg"], "type": 0, "id": 1085025}, {"image_hue": "0x647fb3", "title": "\u70bc\u51fa\u4e2a\u672a\u6765\uff1a\u8dd1\u6b65\u8fd8\u662f\u6e38\u6cf3\u8fd8\u662f\u8dd1\u6b65\u8fd8\u662f\u6e38\u6cf3\u8fd8\u662f\u8dd1\u6b65", "url": "https://daily.zhihu.com/story/1084157", "hint": "\u88d8\u4f2f\u7eafBenjamin \u00b7 1 \u5206\u949f\u9605\u8bfb", "ga_prefix": "092120", "images": ["http://p3.zhimg.com/bc/fb/bcfb280c0ffe3940926fddfffde08512.jpg"], "type": 0, "id": 1084157}, {"image_hue": "0xb37da8", "title": "\u4f5c\u6587\u91cc\uff0c\u5168\u5929\u4e0b\u7684\u5988\u5988\u4eec\u90fd\u662f\u5bb6\u653f\u4fdd\u59c6", "url": "https://daily.zhihu.com/story/1083109", "hint": "\u5c1a\u7231\u5170 \u00b7 3 \u5206\u949f\u9605\u8bfb", "ga_prefix": "092119", "images": ["http://p2.zhimg.com/e6/70/e6701510be59d85cccaa9c658dd16b2a.jpg"], "type": 0, "id": 1083109}, {"image_hue": "0xb39c7d", "title": "\u4e0d\u8981\u518d\u5e26\u67aa\u5230\u5e97\u91cc\u6765\uff01\u661f\u5df4\u514b\u8001\u677f\u6073\u8bf7\u987e\u5ba2", "url": "https://daily.zhihu.com/story/1082805", "hint": "talich \u00b7 1 \u5206\u949f\u9605\u8bfb", "ga_prefix": "092118", "images": ["http://p3.zhimg.com/f1/87/f1878857309d41d876c85c4fd6c40372.jpg"], "type": 0, "id": 1082805}, {"image_hue": "0x524939", "title": "iOS 7 \u6b63\u5f0f\u7248\u521d\u4f53\u9a8c\uff1a\u505a\u5148\u5403\u8783\u87f9\u7684\u4eba\uff0c\u8bd5\u4e00\u8bd5\u597d\u4e0d\u597d\u5403", "url": "https://daily.zhihu.com/story/1082739", "hint": "Reason \u00b7 2 \u5206\u949f\u9605\u8bfb", "ga_prefix": "092117", "images": ["http://p1.zhimg.com/06/1d/061d303005bb985fc3232f27359b2002.jpg"], "type": 0, "id": 1082739}, {"image_hue": "0x7b86b0", "title": "\u8bfb\u4e0d\u591f \u00b7 \u4ec0\u4e48\u65f6\u5019\u8bfb\u51e1\u5c14\u7eb3\u7684\u5c0f\u8bf4\uff0c\u90fd\u6b63\u597d", "url": "https://daily.zhihu.com/story/1080996", "hint": "\u674e\u6698 \u00b7 5 \u5206\u949f\u9605\u8bfb", "ga_prefix": "092114", "images": ["http://p1.zhimg.com/0a/1d/0a1d60448e3e694e82684260f216c847.jpg"], "type": 0, "id": 1080996}, {"image_hue": "0xa5764e", "title": "\u8bfb\u4e0d\u591f \u00b7 \u6495\u6389\u8fd9\u4e9b\u70c2\u5c01\u76ae\u513f\uff0c\u6574\u4e2a\u4e16\u754c\u5c31\u5e72\u51c0\u4e86", "url": "https://daily.zhihu.com/story/1081842", "hint": "\u6c6a\u9759\u59dd \u00b7 1 \u5206\u949f\u9605\u8bfb", "ga_prefix": "092114", "images": ["http://p2.zhimg.com/5c/fa/5cfa4e5f32c986701ff38d1426c8c299.jpg"], "type": 0, "id": 1081842}, {"image_hue": "0x9eb37d", "title": "\u8bfb\u4e0d\u591f \u00b7 \u77ed\uff0c\u4f46\u662f\u5f88\u5999", "url": "https://daily.zhihu.com/story/1081269", "hint": "\u848b\u65b9\u821f \u00b7 1 \u5206\u949f\u9605\u8bfb", "ga_prefix": "092114", "images": ["http://p3.zhimg.com/b2/d7/b2d79b6ba4a53022af5eda626cca1551.jpg"], "type": 0, "id": 1081269}, {"image_hue": "0x382d27", "title": "\u7ea6\u4e2a\u4f1a \u00b7 \u5403\u996d\u7684\u65f6\u5019\u633a\u5f00\u5fc3\uff0c\u7ed3\u8d26\u7684\u65f6\u5019\u72af\u4e86\u6101", "url": "https://daily.zhihu.com/story/1063627", "hint": "\u8d1f\u4e8c \u00b7 3 \u5206\u949f\u9605\u8bfb", "ga_prefix": "092111", "images": ["http://p1.zhimg.com/d0/eb/d0ebe0081366595b197550dd33b101de.jpg"], "type": 0, "id": 1063627}, {"image_hue": "0x9f664a", "title": "\u7ea6\u4e2a\u4f1a \u00b7 \u521d\u6b21\u89c1\u9762\uff0c\u6709\u4e00\u95e8\u5b66\u79d1\u53eb\u505a\u300c\u597d\u611f\u5b66\u300d", "url": "https://daily.zhihu.com/story/1074622", "hint": "\u5f20\u6625 \u00b7 6 \u5206\u949f\u9605\u8bfb", "ga_prefix": "092111", "images": ["http://p2.zhimg.com/e2/89/e289128433981f1cc018edbba90d69e5.jpg"], "type": 0, "id": 1074622}, {"image_hue": "0xab650c", "title": "\u7ea6\u4e2a\u4f1a \u00b7 \u7ea6\u65b0\u8ba4\u8bc6\u7684\u5973\u53cb\u6765\u5bb6\u5403\u996d\uff0c\u996d\u540e\u4e0b\u4e94\u5b50\u68cb\u53ef\u4ee5\u5417\uff1f", "url": "https://daily.zhihu.com/story/1063352", "hint": "\u6731\u6021\u5a67 \u00b7 1 \u5206\u949f\u9605\u8bfb", "ga_prefix": "092111", "images": ["http://p4.zhimg.com/35/0b/350b2718aeac5165a1c106b1e65f2ce9.jpg"], "type": 0, "id": 1063352}, {"image_hue": "", "title": "\u4f17\u4e50\u4e50 \u00b7 \u8e0f\u79cb\uff1a\u722c\u4e2a\u5c0f\u5c71\u804a\u4e2a\u5929\uff0c\u73a9\u73a9\u987a\u4fbf\u953b\u70bc", "url": "https://daily.zhihu.com/story/1082430", "hint": "\u4f59\u548c\u5e73 \u00b7 1 \u5206\u949f\u9605\u8bfb", "ga_prefix": "092108", "images": ["http://p3.zhimg.com/f1/69/f16983730a4cf5cc3dcc2dbfe7a5f468.jpg"], "type": 0, "id": 1082430}, {"image_hue": "0xb3a87d", "title": "\u4f17\u4e50\u4e50 \u00b7 \u563f\u9192\u9192\uff0c\u51fa\u884c\u8def\u4e0a\u522b\u53ea\u987e\u7740\u7761\u89c9", "url": "https://daily.zhihu.com/story/1076187", "hint": "\u96c1\u6e21 \u00b7 1 \u5206\u949f\u9605\u8bfb", "ga_prefix": "092108", "images": ["http://p4.zhimg.com/37/f9/37f99c0bc99015327b6a35cbba59d40b.jpg"], "type": 0, "id": 1076187}, {"image_hue": "0x2a1d1b", "title": "\u4f17\u4e50\u4e50 \u00b7 \u624b\u673a\u653e\u4e0b\uff0ciPad \u62ff\u6765\uff0c\u5927\u5bb6\u4e00\u8d77\u73a9", "url": "https://daily.zhihu.com/story/1075563", "hint": "\u77e5\u4e4e\u7528\u6237 \u00b7 1 \u5206\u949f\u9605\u8bfb", "ga_prefix": "092108", "images": ["http://p4.zhimg.com/c2/38/c238e30b72362498fc123d37a760060c.jpg"], "type": 0, "id": 1075563}]}