{"date": "20191030", "stories": [{"image_hue": "0x1f3b76", "title": "\u524d\u6cbf\u79d1\u5b66\u7684\u53d1\u5c55\u7a76\u7adf\u80fd\u6709\u591a\u8d85\u4e4e\u60f3\u8c61\uff1f", "url": "https://daily.zhihu.com/story/9716777", "hint": "\u5218\u535a\u6d0b \u00b7 3 \u5206\u949f\u9605\u8bfb", "ga_prefix": "103020", "images": ["https://pic3.zhimg.com/v2-0d39435eb19a312bc66b13dbbc49ceda.jpg"], "type": 0, "id": 9716777}, {"image_hue": "0xb39378", "title": "\u4e3a\u4ec0\u4e48\u73b0\u5728\u7684 90 \u540e\u5458\u5de5\u666e\u904d\u90fd\u4e0d\u613f\u610f\u5df4\u7ed3\u9886\u5bfc\uff1f", "url": "https://daily.zhihu.com/story/9716850", "hint": "\u7a7a\u767d\u767d\u767d\u767d \u00b7 7 \u5206\u949f\u9605\u8bfb", "ga_prefix": "103016", "images": ["https://pic2.zhimg.com/v2-de32c222aa7f41005291ab3d4ed64679.jpg"], "type": 0, "id": 9716850}, {"image_hue": "0xb3a17d", "title": "\u5982\u4f55\u770b\u5f85\u5ba0\u7269\u5496\u5561\u9986\u5c06\u5ba0\u7269\u72ac\u67d3\u8272\u6210\u718a\u732b\u72d7\uff0c\u5ba0\u7269\u7f8e\u5bb9\u7684\u5c3a\u5ea6\u5728\u54ea\uff1f", "url": "https://daily.zhihu.com/story/9716696", "hint": "\u5982\u831c \u00b7 1 \u5206\u949f\u9605\u8bfb", "ga_prefix": "103009", "images": ["https://pic1.zhimg.com/v2-9c13c7390d07841b31ebb77eadf3ccf4.jpg"], "type": 0, "id": 9716696}, {"image_hue": "0x514437", "title": "\u4e3a\u4ec0\u4e48\u7f8e\u6f2b\u91cc\u6709\u5f88\u591a\u666e\u901a\u4eba\u80fd\u6253\u8d25\u8d85\u80fd\u529b\u8005\u7684\u60c5\u51b5\uff0c\u56fd\u6f2b\u65e5\u6f2b\u5374\u51e0\u4e4e\u6ca1\u6709\uff1f", "url": "https://daily.zhihu.com/story/9716689", "hint": "\u8bb8\u591a\u7684\u5c0f\u5175\u5668 \u00b7 2 \u5206\u949f\u9605\u8bfb", "ga_prefix": "103007", "images": ["https://pic3.zhimg.com/v2-1fafc6449db20e2968453ec87ebb6e66.jpg"], "type": 0, "id": 9716689}, {"image_hue": "0x98b37d", "title": "\u778e\u626f \u00b7 \u5982\u4f55\u6b63\u786e\u5730\u5410\u69fd", "url": "https://daily.zhihu.com/story/9716832", "hint": "VOL.2250", "ga_prefix": "103006", "images": ["https://pic2.zhimg.com/v2-0b993f827b910d2c7a2d7b2a0ae3d07d.jpg"], "type": 0, "id": 9716832}]}