{"date": "20150330", "stories": [{"image_hue": "0x473732", "title": "\u6df1\u591c\u60ca\u5947 \u00b7 \u4e25\u91cd\u5de5\u4f24", "url": "https://daily.zhihu.com/story/4630764", "hint": "\u9ad8\u533b\u751f\u6709\u62d6\u5ef6\u75c7 \u00b7 3 \u5206\u949f\u9605\u8bfb", "ga_prefix": "033022", "images": ["http://pic1.zhimg.com/06ffc4bafa568c6dbec28dfc99a3c8c0.jpg"], "type": 0, "id": 4630764}, {"image_hue": "0xb38b7d", "title": "\u5982\u4f55\u5feb\u901f\u63d0\u9ad8\u81ea\u5df1\u7684\u89c2\u5f71\u91cf\uff1f", "url": "https://daily.zhihu.com/story/4629850", "hint": "\u77e5\u4e4e\u7528\u6237 \u00b7 4 \u5206\u949f\u9605\u8bfb", "ga_prefix": "033021", "images": ["http://pic3.zhimg.com/481e62750a4faa3135c0949937f24c1a.jpg"], "type": 0, "id": 4629850}, {"image_hue": "0x877db3", "title": "\u4e09\u56fd\u6700\u5927\u4eba\u751f\u8d62\u5bb6\uff1a\u738b\u6717\u738b\u53f8\u5f92", "url": "https://daily.zhihu.com/story/4630469", "hint": "\u5f20\u4f73\u73ae \u00b7 4 \u5206\u949f\u9605\u8bfb", "ga_prefix": "033020", "images": ["http://pic3.zhimg.com/a45d5894ae15b9e8e5ec0123b3ead54e.jpg"], "type": 0, "id": 4630469}, {"image_hue": "0xb3987d", "title": "\u7537\u751f\u9700\u8981\u7684\u57fa\u672c\u6b3e\u88e4\u5b50\u6709\u54ea\u4e9b\uff1f", "url": "https://daily.zhihu.com/story/4602305", "hint": "\u675c\u7ecd\u6590 \u00b7 6 \u5206\u949f\u9605\u8bfb", "ga_prefix": "033019", "images": ["http://pic1.zhimg.com/9cdeff07cd9b011b4fa3c3efce893f34.jpg"], "multipic": true, "type": 0, "id": 4602305}, {"image_hue": "0xb39c7d", "title": "\u5230\u5904\u90fd\u6709\u4e0d\u540c\u7684\u5473\u564c\uff0c\u6211\u8be5\u600e\u4e48\u9009\uff1f", "url": "https://daily.zhihu.com/story/4631100", "hint": "King Kismet \u00b7 1 \u5206\u949f\u9605\u8bfb", "ga_prefix": "033018", "images": ["http://pic4.zhimg.com/5417bb69050dc0e2d174e7e8cd205827.jpg"], "type": 0, "id": 4631100}, {"image_hue": "0xb3977d", "title": "\u997f\u4e86 \u00b7 \u7ffb\u4e86\u5f88\u591a\u4e66\uff0c\u53d1\u73b0\u4e86\u9ad8\u8d28\u91cf\u9f99\u4e95\u867e\u4ec1\u7684\u5965\u4e49", "url": "https://daily.zhihu.com/story/4590011", "hint": "\u65e0\u4e0d\u6563\u5e2d \u00b7 1 \u5206\u949f\u9605\u8bfb", "ga_prefix": "033017", "images": ["http://pic2.zhimg.com/a8d30f830160ec8d729c52fbcf1aac69.jpg"], "type": 0, "id": 4590011}, {"image_hue": "0x332924", "title": "\u300a\u738b\u724c\u7279\u5de5\u300b\u4e4b\u738b\u724c\u88c5\u5907\uff1a\u95f7\u9a9a\u800d\u5e05\u5c31\u9760\u5b83\u4eec\uff08\u591a\u56fe\uff09", "url": "https://daily.zhihu.com/story/4630597", "hint": "\u514b\u52d2kk \u00b7 6 \u5206\u949f\u9605\u8bfb", "ga_prefix": "033016", "images": ["http://pic4.zhimg.com/40f88e6d8c46db4b204f0077f0fac7ff.jpg"], "multipic": true, "type": 0, "id": 4630597}, {"image_hue": "0xb38d7d", "title": "\u4f18\u79c0\u7684\u8c08\u5224\u8005\u901a\u5e38\u5177\u6709\u54ea\u4e9b\u7279\u8d28\uff1f", "url": "https://daily.zhihu.com/story/4630446", "hint": "SeanTan\u53c8\u540d\u65fa\u8d22 \u00b7 1 \u5206\u949f\u9605\u8bfb", "ga_prefix": "033015", "images": ["http://pic1.zhimg.com/303db3aa60c097625896a16928d43c68.jpg"], "type": 0, "id": 4630446}, {"image_hue": "0xb38264", "title": "\u6392\u5f88\u957f\u961f\u7684\u90a3\u79cd\u9910\u5385\u662f\u600e\u6837\u70bc\u6210\u7684", "url": "https://daily.zhihu.com/story/4612926", "hint": "Lecember \u00b7 2 \u5206\u949f\u9605\u8bfb", "ga_prefix": "033014", "images": ["http://pic2.zhimg.com/aa6840fd4f55a9c45b815e2c9fa1872d.jpg"], "type": 0, "id": 4612926}, {"image_hue": "0x3b3028", "title": "2015 \u5e74\u521d\u662f\u4ec0\u4e48\u539f\u56e0\u5bfc\u81f4\u5404\u5927\u5916\u4f01\u64a4\u79bb\u4e2d\u56fd\uff1f", "url": "https://daily.zhihu.com/story/4627818", "hint": "\u77e5\u4e4e\u7528\u6237 \u00b7 1 \u5206\u949f\u9605\u8bfb", "ga_prefix": "033013", "images": ["http://pic1.zhimg.com/c244b446b2c1791822a319c391808820.jpg"], "type": 0, "id": 4627818}, {"image_hue": "0x987db3", "title": "\u300a\u6211\u662f\u6b4c\u624b\u300b\u603b\u51b3\u8d5b\u7b2c\u4e00\u8f6e\uff1a\u5177\u4f53\u5206\u6790\u5e2e\u5e2e\u5531", "url": "https://daily.zhihu.com/story/4630385", "hint": "\u9093\u67ef \u00b7 8 \u5206\u949f\u9605\u8bfb", "ga_prefix": "033012", "images": ["http://pic2.zhimg.com/e59104fa81e4dd27a10aac6f7daa919d.jpg"], "type": 0, "id": 4630385}, {"image_hue": "0x968169", "title": "\u5373\u4f7f\u5728\u4e8c\u6b21\u5143\u53d1\u6e90\u5730\u7684\u65e5\u672c\uff0cACG \u4e5f\u662f\u5c0f\u4f17\u7684\u7231\u597d\u5417\uff1f", "url": "https://daily.zhihu.com/story/4630134", "hint": "\u82cf\u83f2 \u00b7 2 \u5206\u949f\u9605\u8bfb", "ga_prefix": "033011", "images": ["http://pic2.zhimg.com/feae9128b1edb4cda3834fd3036aa71d.jpg"], "type": 0, "id": 4630134}, {"image_hue": "0xb39c7d", "title": "\u5927\u5bb6\u90fd\u5728\u7422\u78e8\u600e\u4e48\u5ba4\u5185\u5b9a\u4f4d\uff0c\u4f46\u6682\u65f6\u6ca1\u4ec0\u4e48\u597d\u65b9\u6cd5", "url": "https://daily.zhihu.com/story/4628820", "hint": "\u738b\u601d\u4f26 \u00b7 2 \u5206\u949f\u9605\u8bfb", "ga_prefix": "033010", "images": ["http://pic4.zhimg.com/aac5b497cc903babf5e4e902b29238eb.jpg"], "type": 0, "id": 4628820}, {"image_hue": "0xb3987d", "title": "\u533b\u9662\u91cc\u547c\u5438\u673a\u88ab\u62d4\u7535\u6e90\u8fd9\u79cd\u72d7\u8840\u5267\u60c5\uff0c\u771f\u7684\u4f1a\u53d1\u751f\u5417\uff1f", "url": "https://daily.zhihu.com/story/4630019", "hint": "\u7ae5\u5fc3 \u00b7 2 \u5206\u949f\u9605\u8bfb", "ga_prefix": "033009", "images": ["http://pic2.zhimg.com/9bcb592872347400c97cee535983d8d1.jpg"], "type": 0, "id": 4630019}, {"image_hue": "0x198790", "title": "\u600e\u6837\u5408\u7406\u5730\u9a8c\u8bc1\u4e00\u4e2a\u7fa4\u4f53\u662f\u5426\u53d7\u5230\u4e86\u6b67\u89c6\uff1f", "url": "https://daily.zhihu.com/story/4629467", "hint": "\u4f55\u5361\u5361 \u00b7 4 \u5206\u949f\u9605\u8bfb", "ga_prefix": "033008", "images": ["http://pic1.zhimg.com/249f52cd2ff128bbda6cf5ff8672c7f0.jpg"], "type": 0, "id": 4629467}, {"image_hue": "0xb37d7d", "title": "\u6709\u52c7\u6c14\u62d2\u7edd\u522b\u4eba\u65f6\uff0c\u52a9\u4eba\u624d\u662f\u51fa\u81ea\u6211\u4eec\u7684\u5584\u610f", "url": "https://daily.zhihu.com/story/4630058", "hint": "\u52a8\u673a\u5728\u676d\u5dde \u00b7 3 \u5206\u949f\u9605\u8bfb", "ga_prefix": "033007", "images": ["http://pic3.zhimg.com/fdf7239c197858c5ddf760605fbae41e.jpg"], "type": 0, "id": 4630058}, {"image_hue": "0x313746", "title": "\u54ea\u4e9b\u4eba\u53ef\u80fd\u4f1a\u4e70 12.68 \u4e07\u7684 Apple Watch Edition", "url": "https://daily.zhihu.com/story/4625874", "hint": "Yi Wang \u00b7 12 \u5206\u949f\u9605\u8bfb", "ga_prefix": "033007", "images": ["http://pic4.zhimg.com/64a6408c674bb41c368045c9125de25f.jpg"], "type": 0, "id": 4625874}, {"image_hue": "0xb37d44", "title": "\u77ed\u65f6\u95f4\u5185\uff0c\u4e0d\u4e89\u6c14\u7684\u4eba\u7c7b\u662f\u5fd8\u4e0d\u4e86\u5bf9\u5783\u573e\u98df\u54c1\u7684\u7231\u7684", "url": "https://daily.zhihu.com/story/4629903", "hint": "Lewind \u00b7 1 \u5206\u949f\u9605\u8bfb", "ga_prefix": "033007", "images": ["http://pic2.zhimg.com/bed27f019f817f344a127a2010a26259.jpg"], "type": 0, "id": 4629903}, {"image_hue": "0x432816", "title": "\u778e\u626f \u00b7 \u5982\u4f55\u6b63\u786e\u5730\u5410\u69fd", "url": "https://daily.zhihu.com/story/4630227", "hint": "VOL.624", "ga_prefix": "033006", "images": ["http://pic4.zhimg.com/51bc7e761dd801a56d599dd2e1f3b3ab.jpg"], "type": 0, "id": 4630227}]}