{"date": "20130724", "stories": [{"image_hue": "0xb35549", "title": "\u6df1\u591c\u98df\u5802 \u00b7 \u9b3c\u95e8\u5173", "url": "https://daily.zhihu.com/story/1769", "hint": "\u533f\u540d\u7528\u6237 \u00b7 3 \u5206\u949f\u9605\u8bfb", "ga_prefix": "072423", "images": ["http://p2.zhimg.com/5e/f3/5ef3e1f6f86652bcf6286810988b48fd.jpg"], "type": 0, "id": 1769}, {"image_hue": "0xb37f7d", "title": "\u975e\u5e38\u5b8f\u5927\u7684\u95ee\u9898\uff1a\u9886\u5e26\u3001\u9886\u7ed3\u3001\u4e1d\u5dfe\u600e\u4e48\u4f69\u6234\u624d\u662f\u6b63\u786e\u7684", "url": "https://daily.zhihu.com/story/1770", "hint": "\u845b\u5dfe \u00b7 3 \u5206\u949f\u9605\u8bfb", "ga_prefix": "072422", "images": ["http://p2.zhimg.com/55/84/55846da4b6720c17b6c0e426240d8d73.jpg"], "type": 0, "id": 1770}, {"image_hue": "0xa38672", "title": "\u9a6c\u4f2f\u5eb8\u4e13\u680f \u00b7 \u6211\u8bfb\u4e66\u5c11\r\n\u5496\u5561\u5728\u4e2d\u56fd\u7684\u5047\u60f3\u53f2\uff08\u4e09\uff09", "url": "https://daily.zhihu.com/story/1775", "hint": "\u9a6c\u4f2f\u5eb8 \u00b7 3 \u5206\u949f\u9605\u8bfb", "ga_prefix": "072421", "images": ["http://p2.zhimg.com/94/34/94344a9f5f99c7bb342884dcc857ea28.jpg"], "type": 0, "id": 1775}, {"image_hue": "0x252736", "title": "\u5c0f\u9053\u6d88\u606f \u00b7 \u4f60\u80fd\u66ff\u6211\u4fdd\u5bc6\u4e48\uff1f", "url": "https://daily.zhihu.com/story/1777", "hint": "Fenng \u00b7 1 \u5206\u949f\u9605\u8bfb", "ga_prefix": "072421", "images": ["http://p1.zhimg.com/08/ac/08acac048bd5dc1af59782e03a08dbca.jpg"], "type": 0, "id": 1777}, {"image_hue": "0xb3977d", "title": "Windows \u7684\u7b2c\u4e00\u4e2a\u76d8\u53eb C \u76d8\uff0cA \u76d8 B \u76d8\u54ea\u513f\u53bb\u4e86\uff1f", "url": "https://daily.zhihu.com/story/1766", "hint": "cOMMANDO \u00b7 2 \u5206\u949f\u9605\u8bfb", "ga_prefix": "072421", "images": ["http://p4.zhimg.com/7a/79/7a79e17cc1e28d9439c3603b067337bf.jpg"], "type": 0, "id": 1766}, {"image_hue": "0x2e2318", "title": "TBBT \u8003\u636e\u7b2c\u4e8c\u5f39\uff1aPenny \u5230\u76ee\u524d\u4e3a\u6b62\u7761\u8fc7\u4e86\u591a\u5c11\u6c49\u5b50\uff1f", "url": "https://daily.zhihu.com/story/1765", "hint": "\u5f20\u5b87\u8fb0 \u00b7 1 \u5206\u949f\u9605\u8bfb", "ga_prefix": "072420", "images": ["http://p3.zhimg.com/28/f0/28f0ecd5455bee6813a69933702d95f5.jpg"], "type": 0, "id": 1765}, {"image_hue": "0xa79c74", "title": "\u9047\u5230\u8fd9\u79cd\u7535\u4fe1\u8bc8\u9a97\uff0c\u62e6\u90fd\u62e6\u4e0d\u4f4f\u4e00\u80a1\u8111\u7ed9\u9a97\u5b50\u6253\u94b1", "url": "https://daily.zhihu.com/story/1750", "hint": "\u5c0f\u98de\u4fa0guan \u00b7 3 \u5206\u949f\u9605\u8bfb", "ga_prefix": "072419", "images": ["http://p4.zhimg.com/c2/76/c276406808697add44c34c657cde20cc.jpg"], "type": 0, "id": 1750}, {"image_hue": "0x786f54", "title": "\u505a\u4e00\u4e2a\u9a91\u58eb\u2014\u2014\u8bb2\u6587\u660e\uff0c\u61c2\u793c\u8c8c\uff0c\u5f88\u9a84\u50b2", "url": "https://daily.zhihu.com/story/1768", "hint": "\u6bdb\u5947 \u00b7 2 \u5206\u949f\u9605\u8bfb", "ga_prefix": "072418", "images": ["http://p2.zhimg.com/ef/a9/efa9e16201f1a164d20fbcb511c2bd06.jpg"], "type": 0, "id": 1768}, {"image_hue": "0x272727", "title": "\u6700\u7f8e\u5e94\u7528 \u00b7 \u4f60\u771f\u7684\u4f1a\u7528 Google \u6d4f\u89c8\u5668\u5417\uff1f", "url": "https://daily.zhihu.com/story/1761", "hint": "\u9648\u5fd7\u8fdc \u00b7 1 \u5206\u949f\u9605\u8bfb", "ga_prefix": "072417", "images": ["http://p1.zhimg.com/43/04/430483c21b8952cedddcf8ce49bc2cd4.jpg"], "type": 0, "id": 1761}, {"image_hue": "0x9a7e5b", "title": "20 \u74f6\u5564\u9152\u4e0b\u809a\uff0c\u6307\u4e0d\u5b9a\u559d\u51fa\u4e2a\u4ec0\u4e48\u6240\u4ee5\u7136\u6765", "url": "https://daily.zhihu.com/story/1762", "hint": "\u82ae\u5143\u794e \u00b7 1 \u5206\u949f\u9605\u8bfb", "ga_prefix": "072417", "images": ["http://p2.zhimg.com/ad/bb/adbb1172dc4907e2ca5d53790ab624ea.jpg"], "type": 0, "id": 1762}, {"image_hue": "0x57513d", "title": "\u628a\u5404\u5730\u65b9\u8a00\u90fd\u53d6\u6d88\uff0c\u5168\u6362\u6210\u666e\u901a\u8bdd\uff0c\u600e\u4e48\u6837\uff1f", "url": "https://daily.zhihu.com/story/1763", "hint": "poem \u00b7 4 \u5206\u949f\u9605\u8bfb", "ga_prefix": "072416", "images": ["http://p2.zhimg.com/1e/f0/1ef0ef5ab79ab51bd36f05acc203bca6.jpg"], "type": 0, "id": 1763}, {"image_hue": "0xb05a49", "title": "\u4e25\u8083\u8138\uff1a\u4e3a\u4ec0\u4e48\u82f1\u56fd\u7684\u51ef\u7279\u738b\u5983\u4e0d\u5750\u6708\u5b50\uff1f", "url": "https://daily.zhihu.com/story/1759", "hint": "qwertyjing \u00b7 3 \u5206\u949f\u9605\u8bfb", "ga_prefix": "072415", "images": ["http://p2.zhimg.com/99/b7/99b72446fe3500731332b5fbe4920bf6.jpg"], "type": 0, "id": 1759}, {"image_hue": "0x332924", "title": "\u65b0\u6d6a\u63a8\u51fa\u4e86\u65b0\u7ea6\u4eba\u5e94\u7528\uff0c\u542c\u540d\u5b57\u50cf\u5fae\u4fe1\uff0c\u5b9e\u9645\u5bf9\u624b\u662f\u964c\u964c", "url": "https://daily.zhihu.com/story/1760", "hint": "\u77e5\u4e4e\u7528\u6237 \u00b7 2 \u5206\u949f\u9605\u8bfb", "ga_prefix": "072414", "images": ["http://p1.zhimg.com/0c/e2/0ce2de3f4fcd846b2e4269f6da609040.jpg"], "type": 0, "id": 1760}, {"image_hue": "0x62788c", "title": "\u591a\u4e2a\u57ce\u5e02\u81ed\u6c27\u8d85\u6807\u544a\u6025\uff0c\u6bd4 PM 2.5 \u66f4\u9ebb\u70e6\u7684\u6c61\u67d3\u6765\u4e86", "url": "https://daily.zhihu.com/story/1757", "hint": "\u54f2\u6653 \u00b7 1 \u5206\u949f\u9605\u8bfb", "ga_prefix": "072413", "images": ["http://p3.zhimg.com/f8/07/f807117ba3869bb5c5887b21868b18ed.jpg"], "type": 0, "id": 1757}, {"image_hue": "0x8a6a4d", "title": "\u77e5\u5929\u4e0b \u00b7 \u54c6\u5566 A \u68a6\u6539\u540d\u53f2", "url": "https://daily.zhihu.com/story/1758", "hint": "LF\u5929\u5f71 \u00b7 2 \u5206\u949f\u9605\u8bfb", "ga_prefix": "072412", "images": ["http://p2.zhimg.com/1f/6f/1f6ff58bd3651f138b51b4923f8f4f7a.jpg"], "type": 0, "id": 1758}, {"image_hue": "0x141414", "title": "\u88ab\u8fea\u65af\u5c3c\u6536\u8d2d\u540e\uff0c\u795e\u00b7\u76ae\u514b\u65af\uff0c\u4e5f\u7ec8\u4e8e\u53d8\u6210\u4e86\u5e7c\u9f7f\u7ae5\u8bdd\u516c\u53f8", "url": "https://daily.zhihu.com/story/1756", "hint": "Ronnie Xiao \u00b7 5 \u5206\u949f\u9605\u8bfb", "ga_prefix": "072411", "images": ["http://p2.zhimg.com/9d/1e/9d1e3e458b7edc80ce69747cb6f8644a.jpg"], "type": 0, "id": 1756}, {"image_hue": "0x77654f", "title": "\u522b\u8bf4\u65b0\u7684\u5c0f\u738b\u5b50\u4e86\uff0c\u82f1\u56fd\u738b\u5ba4\u7684\u4efb\u4f55\u98ce\u5439\u8349\u52a8\u90fd\u80fd\u4e0a\u5934\u7248", "url": "https://daily.zhihu.com/story/1753", "hint": "Yang Huo \u00b7 4 \u5206\u949f\u9605\u8bfb", "ga_prefix": "072410", "images": ["http://p2.zhimg.com/52/e8/52e8dce8bc50036237de8e36cd233d5d.jpg"], "type": 0, "id": 1753}, {"image_hue": "0x044cb3", "title": "\u62ff\u7d2b\u5916\u7ebf\u706f\u5f53\u7167\u660e\u706f\uff0c\u906d\u5bb3\u7684\u4e0d\u53ea\u662f\u773c\u775b", "url": "https://daily.zhihu.com/story/1752", "hint": "\u738b\u5c0f\u661f \u00b7 1 \u5206\u949f\u9605\u8bfb", "ga_prefix": "072409", "images": ["http://p4.zhimg.com/32/12/3212353041feb6fa915202d9b2ea0b48.jpg"], "type": 0, "id": 1752}, {"image_hue": "0x473234", "title": "\u82f9\u679c\u6536\u8d2d\u65b0\u5730\u56fe\uff0c\u81ea\u5e26\u5730\u56fe\u7ec8\u4e8e\u8981\u6709\u516c\u4ea4\u6362\u4e58\u5efa\u8bae\u4e86\uff1f", "url": "https://daily.zhihu.com/story/1717", "hint": "\u5f20\u5c0f\u5b87 \u00b7 1 \u5206\u949f\u9605\u8bfb", "ga_prefix": "072407", "images": ["http://p3.zhimg.com/f3/5b/f35b22e8c82e0e7399ecff3703838216.jpg"], "type": 0, "id": 1717}, {"image_hue": "0xb37d8f", "title": "360 \u65b0\u4e0a\u7ebf\u4e86\u96f7\u7535\u624b\u673a\u641c\u7d22\uff0c\u7ee7\u7eed\u6b7b\u78d5\u5c0f\u767d\u7528\u6237", "url": "https://daily.zhihu.com/story/1736", "hint": "\u77e5\u4e4e\u7528\u6237 \u00b7 3 \u5206\u949f\u9605\u8bfb", "ga_prefix": "072407", "images": ["http://p2.zhimg.com/e2/58/e258357001f55d3763a52f01df1acdb2.jpg"], "type": 0, "id": 1736}, {"image_hue": "0x2f2b3d", "title": "\u6765\u6765\u6765\uff0c\u5b66\u4e00\u4e2a\u4f60\u80af\u5b9a\u4f1a\u4e0d\u505c\u89c1\u5230\u7684\u65b0\u5355\u8bcd\u2014\u2014Likonomics", "url": "https://daily.zhihu.com/story/1060", "hint": "\u5468\u6653\u519c \u00b7 3 \u5206\u949f\u9605\u8bfb", "ga_prefix": "072407", "images": ["http://p3.zhimg.com/b4/e6/b4e6836db20947288972e73cbc3f0330.jpg"], "type": 0, "id": 1060}, {"image_hue": "0x12121a", "title": "\u5728\u624b\u673a\u4e0a\uff0c\u706b\u7206\u7684\u5355\u673a\u6e38\u620f\u4eec\u628a\u7f51\u6e38\u538b\u5f97\u5598\u4e0d\u8fc7\u6c14\u6765", "url": "https://daily.zhihu.com/story/1748", "hint": "\u91d1\u6cf0\u5b87 \u00b7 3 \u5206\u949f\u9605\u8bfb", "ga_prefix": "072407", "images": ["http://p2.zhimg.com/5f/cb/5fcbcaf4c1f3cccce98ac74f2e1f6497.jpg"], "type": 0, "id": 1748}, {"image_hue": "0x2c2c2c", "title": "\u667a\u80fd\u673a\u5e02\u573a\u54c0\u568e\u4e00\u7247\uff0c\u82f9\u679c\u4e09\u661f\u4eec\u80fd\u5728\u4e2d\u56fd\u5237\u5230\u589e\u957f\u5417\uff1f", "url": "https://daily.zhihu.com/story/1743", "hint": "\u674e\u6012\u653e \u00b7 2 \u5206\u949f\u9605\u8bfb", "ga_prefix": "072407", "images": ["http://p3.zhimg.com/f2/a5/f2a51adf5149e201537e46284576606a.jpg"], "type": 0, "id": 1743}, {"image_hue": "0xb37d7d", "title": "\u778e\u626f \u00b7 \u534a\u4e2a\u6708\u5de5\u8d44\u800c\u5df2", "url": "https://daily.zhihu.com/story/1747", "hint": "VOL.54", "ga_prefix": "072406", "images": ["http://p2.zhimg.com/95/76/9576a51e6139b4a6403e3351c05997d3.jpg"], "type": 0, "id": 1747}]}