{"date": "20150814", "stories": [{"image_hue": "0x805137", "title": "\u6df1\u591c\u60ca\u5947 \u00b7 \u98de\u8dc3\u75af\u4eba\u9662", "url": "https://daily.zhihu.com/story/7047289", "hint": "\u82b1\u5c0f\u5915 \u00b7 4 \u5206\u949f\u9605\u8bfb", "ga_prefix": "081422", "images": ["http://pic4.zhimg.com/833d69ce2258ccad5b25535f05e1fb9b.jpg"], "type": 0, "id": 7047289}, {"image_hue": "0x291d1d", "title": "\u770b\u5b8c\u4e09\u90e8\u300a\u8759\u8760\u4fa0\u524d\u4f20\u300b\uff0c\u522b\u7684\u8d85\u7ea7\u82f1\u96c4\u5c31\u4e0d\u5fc5\u770b\u4e86", "url": "https://daily.zhihu.com/story/7042861", "hint": "\u91cd\u5149\u5148\u751f \u00b7 1 \u5206\u949f\u9605\u8bfb", "ga_prefix": "081421", "images": ["http://pic3.zhimg.com/287b98ec402fd32b42d7ae1fc91d9012.jpg"], "type": 0, "id": 7042861}, {"image_hue": "0xb38f7d", "title": "\u300c\u53ea\u6709\u6211\u5b8c\u7f8e\u4e86\uff0c\u4ed6\u624d\u4f1a\u559c\u6b22\u6211\u5427\u2026\u2026\u300d", "url": "https://daily.zhihu.com/story/4875867", "hint": "Owl of Minerva \u00b7 8 \u5206\u949f\u9605\u8bfb", "ga_prefix": "081420", "images": ["http://pic4.zhimg.com/a9bbb7dd8b690394ca963b7d28aadfaf.jpg"], "type": 0, "id": 4875867}, {"image_hue": "0x0c0607", "title": "\u4eca\u665a\u7684\u4fee\u7834\u65af\u54d2\u662f \u00b7 \u5468\u8fc5", "url": "https://daily.zhihu.com/story/7050612", "hint": "\u4e0d\u544a\u8bc9\u4f60 \u00b7 4 \u5206\u949f\u9605\u8bfb", "ga_prefix": "081419", "images": ["http://pic2.zhimg.com/45f8e310012ba4ffd32806d0095a6595.jpg"], "multipic": true, "type": 0, "id": 7050612}, {"image_hue": "0x342216", "title": "\u5c31\u7b97\u5f53\u5e74\u5eb7\u7199\u5efa\u4e86\u79d1\u5b66\u9662\uff0c\u6e05\u671d\u79bb\u5de5\u4e1a\u9769\u547d\u8fd8\u662f\u5f88\u8fdc", "url": "https://daily.zhihu.com/story/7050298", "hint": "\u6c6a\u6709 \u00b7 4 \u5206\u949f\u9605\u8bfb", "ga_prefix": "081418", "images": ["http://pic4.zhimg.com/1b7a6e1881ccfd1184a1741d357fffdf.jpg"], "type": 0, "id": 7050298}, {"image_hue": "0x040404", "title": "\u6709\u4e86\u8fd9\u4e2a\u83dc\u6211\u80fd\u5403\u4e24\u5927\u7897\u7c73\u996d\uff01\uff08\u8d34\u5fc3\u9644\u4e0a\u505a\u6cd5\uff09", "url": "https://daily.zhihu.com/story/7050198", "hint": "elyn \u00b7 1 \u5206\u949f\u9605\u8bfb", "ga_prefix": "081417", "images": ["http://pic3.zhimg.com/f1dadfb2a476ee0fe822f952f4049d16.jpg"], "multipic": true, "type": 0, "id": 7050198}, {"image_hue": "0x0d0909", "title": "\u6709\u4e9b\u4eba\u8138\u76f2\u53ea\u662f\u8bf4\u8bf4\uff0c\u6709\u4e9b\u4eba\u7684\u8138\u76f2\u2026\u2026\u771f\u7684\u662f\u75c5\u554a", "url": "https://daily.zhihu.com/story/7048522", "hint": "\u6c89\u9ed8\u7684\u9a6c\u5927\u7237 \u00b7 3 \u5206\u949f\u9605\u8bfb", "ga_prefix": "081416", "images": ["http://pic1.zhimg.com/afca44f9392b4532365f32378feb1894.jpg"], "type": 0, "id": 7048522}, {"image_hue": "0xb29173", "title": "\u8eab\u4e3a\u4e00\u4e2a\u5851\u6599\u7247\uff0c\u53d8\u5927\u53d8\u7ea2\u540e\uff0c\u6211\u6210\u4e86\u5357\u5b5a\u300c\u805a\u80fd\u73af\u300d", "url": "https://daily.zhihu.com/story/7050310", "hint": "\u77e5\u4e4e\u7528\u6237 \u00b7 1 \u5206\u949f\u9605\u8bfb", "ga_prefix": "081415", "images": ["http://pic4.zhimg.com/5b3512b17204d69b29b698b80532462b.jpg"], "type": 0, "id": 7050310}, {"image_hue": "0xb3997d", "title": "\u591a\u5bf9\u9999\u70df\u5f81\u70b9\u7a0e\uff0c\u5e7f\u5927\u70df\u6c11\u670b\u53cb\u662f\u4e0d\u662f\u4f1a\u53bb\u4e70\u4fbf\u5b9c\u7684\u70df\uff1f", "url": "https://daily.zhihu.com/story/7050375", "hint": "\u51af\u6657 \u00b7 1 \u5206\u949f\u9605\u8bfb", "ga_prefix": "081414", "images": ["http://pic3.zhimg.com/638a62b0b5e35b05e4ef448c817974e2.jpg"], "type": 0, "id": 7050375}, {"image_hue": "0xb39f7d", "title": "\u53f0\u98ce\u603b\u662f\u5148\u51b2\u8fc7\u6765\uff0c\u7136\u540e\u8f6c\u4e2a\u65b9\u5411\u8d70\u4e86", "url": "https://daily.zhihu.com/story/7049695", "hint": "\u6f20\u5317 \u00b7 2 \u5206\u949f\u9605\u8bfb", "ga_prefix": "081413", "images": ["http://pic4.zhimg.com/211e6eb5038a03faa8ea05b3705143af.jpg"], "type": 0, "id": 7049695}, {"image_hue": "0xb3711b", "title": "\u5982\u679c\u5b9e\u5728\u60f3\u5403\u5feb\u9910\u5783\u573e\u98df\u54c1\uff0c\u7b54\u5e94\u6211\uff0c\u81f3\u5c11\u8fd9\u6837\u5403", "url": "https://daily.zhihu.com/story/7048977", "hint": "\u521d\u590f\u4e4b\u83e1 \u00b7 5 \u5206\u949f\u9605\u8bfb", "ga_prefix": "081412", "images": ["http://pic3.zhimg.com/3822304257ae27624e15d1cbdbf3e9e6.jpg"], "type": 0, "id": 7048977}, {"image_hue": "0xb38b7d", "title": "\u73b0\u5728\uff0c\u8ba9\u6211\u4eec\u804a\u804a\u8fd9\u6b21\u4e8b\u6545\u4e4b\u540e\u7684\u5fc3\u7406\u6551\u52a9", "url": "https://daily.zhihu.com/story/7049548", "hint": "\u53f6\u58ee \u00b7 5 \u5206\u949f\u9605\u8bfb", "ga_prefix": "081411", "images": ["http://pic2.zhimg.com/102de22f7b5aa69d00d2f89808d03c79.jpg"], "type": 0, "id": 7049548}, {"image_hue": "0x253630", "title": "\u8c37\u6b4c\u3001\u5fae\u8f6f\u548c\u8bfa\u57fa\u4e9a\u7684 CEO \u90fd\u6765\u81ea\u5370\u5ea6\uff0c\u4ed6\u4eec\u7684\u4f18\u52bf\u5728\u54ea\u91cc\uff1f", "url": "https://daily.zhihu.com/story/7049702", "hint": "\u5f20\u777f \u00b7 1 \u5206\u949f\u9605\u8bfb", "ga_prefix": "081410", "images": ["http://pic4.zhimg.com/a7eb16228db31531d971315035a9e98b.jpg"], "type": 0, "id": 7049702}, {"image_hue": "0xab9c78", "title": "\u6709\u4e9b\u4e8b\u660e\u77e5\u9053\u6709\u5bb3\uff0c\u4f46\u6211\u8fd8\u662f\u8981\u53bb\u505a", "url": "https://daily.zhihu.com/story/7043461", "hint": "\u6539\u4e4b\u7406zcw \u00b7 2 \u5206\u949f\u9605\u8bfb", "ga_prefix": "081409", "images": ["http://pic2.zhimg.com/48f5271531ecaf7960b17f29f95069e1.jpg"], "type": 0, "id": 7043461}, {"image_hue": "0x7db3a2", "title": "\u8981\u662f\u8fdb\u53e3\u8d27\u90fd\u4e0d\u7528\u5173\u7a0e\uff0c\u6709\u94b1\u4eba\u548c\u7a77\u4eba\u5dee\u5f97\u4f1a\u5c0f\u90a3\u4e48\u4e00\u4e22\u4e22\u5417\uff1f", "url": "https://daily.zhihu.com/story/7049687", "hint": "\u6539\u4e4b\u7406zcw \u00b7 6 \u5206\u949f\u9605\u8bfb", "ga_prefix": "081408", "images": ["http://pic3.zhimg.com/959f3a3085e4c8f216c1b1b9b09839f6.jpg"], "type": 0, "id": 7049687}, {"image_hue": "0x080605", "title": "\u54ed\u4e86\u4e00\u4f1a\u513f\uff0c\u773c\u775b\u80bf\u6210\u6843\uff0c\u600e\u4e48\u56de\u4e8b\u5462", "url": "https://daily.zhihu.com/story/7049646", "hint": "\u77e5\u4e4e\u7528\u6237 \u00b7 1 \u5206\u949f\u9605\u8bfb", "ga_prefix": "081407", "images": ["http://pic1.zhimg.com/1b64790b1a47afca26d1427783af0604.jpg"], "type": 0, "id": 7049646}, {"image_hue": "0xb39a69", "title": "\u4e2d\u56fd\u4e3a\u4ec0\u4e48\u4e0d\u91c7\u7528\u804c\u4e1a\u5316\u7684\u6d88\u9632\u5458\uff1f", "url": "https://daily.zhihu.com/story/7048966", "hint": "\u6728\u7389\u826f \u00b7 6 \u5206\u949f\u9605\u8bfb", "ga_prefix": "081407", "images": ["http://pic1.zhimg.com/f4a4235cc37185b239f7d73dcb8c64fc.jpg"], "type": 0, "id": 7048966}, {"image_hue": "0xb3a57d", "title": "\u7206\u70b8\u9707\u7834\u5185\u810f\uff0c\u5f53\u65f6\u770b\u4e0d\u51fa\u6765\uff0c\u4e0d\u4e45\u5c31\u6b7b\u4e86\u2014\u2014\u53c8\u662f\u8c23\u8a00", "url": "https://daily.zhihu.com/story/7048927", "hint": "\u77e5\u4e4e\u7528\u6237 \u00b7 1 \u5206\u949f\u9605\u8bfb", "ga_prefix": "081407", "images": ["http://pic4.zhimg.com/6e0676dde6f3abd5b2856af0ae6e405b.jpg"], "type": 0, "id": 7048927}, {"image_hue": "0xb37db3", "title": "\u778e\u626f \u00b7 \u5982\u4f55\u6b63\u786e\u5730\u5410\u69fd", "url": "https://daily.zhihu.com/story/7047267", "hint": "VOL.761", "ga_prefix": "081406", "images": ["http://pic4.zhimg.com/144d9ca409be0c12591915a9fcbdf007.jpg"], "type": 0, "id": 7047267}]}