{"date": "20161216", "stories": [{"image_hue": "0x675547", "title": "\u5c0f\u4e8b \u00b7 \u5f00\u8b66\u8f66\u4e86\u4e0d\u8d77\u554a", "url": "https://daily.zhihu.com/story/9071484", "hint": "VOL.198", "ga_prefix": "121622", "images": ["http://pic2.zhimg.com/d71689c029cf9074984fe2ac60ea14d9.jpg"], "multipic": true, "type": 0, "id": 9071484}, {"image_hue": "0x2b2b3d", "title": "\u4e0d\u7528\u7279\u6548\uff0c\u4e0d\u7528\u5316\u5986\uff0c\u4f60\u4e5f\u80fd\u611f\u53d7\u5230\u9b54\u9b3c\u7684\u53ef\u6015", "url": "https://daily.zhihu.com/story/9071426", "hint": "\u738b\u5199\u5199 \u00b7 7 \u5206\u949f\u9605\u8bfb", "ga_prefix": "121621", "images": ["http://pic3.zhimg.com/7a484a1ccc16efe6abd57142d1841a4a.jpg"], "type": 0, "id": 9071426}, {"image_hue": "0xb3917d", "title": "\u4e3a\u4ec0\u4e48\u662f\u300c\u65e0\u507f\u732e\u8840\u300d\uff1f\u732e\u8840\u4e0d\u80fd\u5e02\u573a\u5316\u5417\uff1f", "url": "https://daily.zhihu.com/story/9069552", "hint": "Manolo \u00b7 2 \u5206\u949f\u9605\u8bfb", "ga_prefix": "121620", "images": ["http://pic1.zhimg.com/63a6688c63037ea6260da9e7f48e6e54.jpg"], "type": 0, "id": 9069552}, {"image_hue": "0x98b37d", "title": "\u4e00\u70b9\u8fd9\u4e2a\u5c0f\u89c6\u9891\uff0c\u6211\u7684 iPhone \u5c31\u6b7b\u673a\u4e86\u2026\u2026", "url": "https://daily.zhihu.com/story/9071303", "hint": "\u77e5\u4e4e\u7528\u6237 \u00b7 1 \u5206\u949f\u9605\u8bfb", "ga_prefix": "121619", "images": ["http://pic4.zhimg.com/6a4c6ad4580549645264ed9d9155854f.jpg"], "type": 0, "id": 9071303}, {"image_hue": "0x7d91b3", "title": "\u80fd\u8ba9\u7ea2\u8272\u9884\u8b66\u542f\u52a8\u7684\u96fe\u973e\uff0c\u662f\u4ece\u54ea\u513f\u6765\u7684\uff1f", "url": "https://daily.zhihu.com/story/9071721", "hint": "\u5510\u6587\u97ec \u00b7 3 \u5206\u949f\u9605\u8bfb", "ga_prefix": "121618", "images": ["http://pic3.zhimg.com/34aa1252737e678ee1a87758f8243e96.jpg"], "type": 0, "id": 9071721}, {"image_hue": "0xb3a07d", "title": "\u77e5\u4e4e\u597d\u95ee\u9898 \u00b7 \u6709\u54ea\u4e9b\u5f88\u91cd\u8981\u5374\u88ab\u5ffd\u89c6\u7684\u7092\u83dc\u6280\u5de7\uff1f", "url": "https://daily.zhihu.com/story/9071610", "hint": " \u00b7 1 \u5206\u949f\u9605\u8bfb", "ga_prefix": "121617", "images": ["http://pic3.zhimg.com/24514abdd68befd1955746b27734bcd6.jpg"], "type": 0, "id": 9071610}, {"image_hue": "0x0f0c12", "title": "\u4e0d\u53bb\u4e0a\u8bfe\uff0c\u5728\u5bb6\u91cc\u770b VR \u89c6\u9891\u81ea\u5b66\u591a\u597d\u2026\u2026", "url": "https://daily.zhihu.com/story/9071495", "hint": "\u51fa\u585e\u66f2 \u00b7 1 \u5206\u949f\u9605\u8bfb", "ga_prefix": "121616", "images": ["http://pic2.zhimg.com/c687c0e431606d4502c8812105dbce79.jpg"], "type": 0, "id": 9071495}, {"image_hue": "0x3d1e28", "title": "\u5728\u4ed6\u7684\u544a\u522b\u5f0f\u4e0a\uff0c\u6bcf\u4e2a\u4eba\u4e5f\u8bb8\u90fd\u4f1a\u7a7f\u4e0a\u8272\u5f69\u6591\u6593\u7684\u897f\u88c5", "url": "https://daily.zhihu.com/story/9070960", "hint": "\u4e4c\u6f6e \u00b7 10 \u5206\u949f\u9605\u8bfb", "ga_prefix": "121615", "images": ["http://pic2.zhimg.com/f0eac3b6af6a83f0ac22167b507de81d.jpg"], "multipic": true, "type": 0, "id": 9070960}, {"image_hue": "0x7ea75e", "title": "iPhone \u4e0a\u4e5f\u53ef\u4ee5\u73a9\u8d85\u7ea7\u9a6c\u91cc\u5965\u5566\uff0c\u8fd9\u6b21\u4e0d\u53ea\u662f\u60c5\u6000", "url": "https://daily.zhihu.com/story/9071031", "hint": "AppSo \u00b7 4 \u5206\u949f\u9605\u8bfb", "ga_prefix": "121614", "images": ["http://pic3.zhimg.com/72685830dde7c4502491795319b1ef1e.jpg"], "multipic": true, "type": 0, "id": 9071031}, {"image_hue": "0xb3927d", "title": "\u5176\u5b9e\u5f02\u6027\u4f20\u64ad\u827e\u6ecb\u75c5\u5360\u4e86\u5927\u5934\uff0c\u4e0d\u8fc7\u7537\u7537\u6027\u4f20\u64ad\u589e\u957f\u5f88\u5feb", "url": "https://daily.zhihu.com/story/9070986", "hint": "\u5468\u533b\u751f \u00b7 1 \u5206\u949f\u9605\u8bfb", "ga_prefix": "121613", "images": ["http://pic1.zhimg.com/f38a43649e0b15d3d67ad4aeb81686dc.jpg"], "type": 0, "id": 9070986}, {"image_hue": "0x836751", "title": "\u5927\u8bef \u00b7 \u60f3\u73a9\u98de\u884c\u68cb\u7684\u4e3e\u624b\ud83d\ude4b", "url": "https://daily.zhihu.com/story/9065027", "hint": "12dora \u00b7 2 \u5206\u949f\u9605\u8bfb", "ga_prefix": "121612", "images": ["http://pic1.zhimg.com/5f8909a9d6100c7b8d358f6430ff810c.jpg"], "type": 0, "id": 9065027}, {"image_hue": "0x9db37d", "title": "\u5728\u300c\u7535\u8f66\u4e4b\u56fd\u300d\uff0c\u65c5\u884c\u7684\u610f\u4e49\u85cf\u5728\u8fd9\u56db\u4ef6\u5c0f\u4e8b\u91cc", "url": "https://daily.zhihu.com/story/9069568", "hint": "\u534a\u5c9b\u541b \u00b7 3 \u5206\u949f\u9605\u8bfb", "ga_prefix": "121611", "images": ["http://pic4.zhimg.com/a04d96d84a6a71d33d0e4c928ccb76bf.jpg"], "multipic": true, "type": 0, "id": 9069568}, {"image_hue": "0x362e42", "title": "\u65e0\u610f\u4e2d\u649e\u5230\u4e8c\u624b\u8f66\u62fc\u63a5\u8fc7\u7a0b\uff0c\u4e70\u8f66\u65f6\u53ef\u8981\u591a\u7559\u5fc3", "url": "https://daily.zhihu.com/story/9069864", "hint": "CPF \u00b7 2 \u5206\u949f\u9605\u8bfb", "ga_prefix": "121610", "images": ["http://pic1.zhimg.com/875b5a9c89d88ee61ae672f51dcae940.jpg"], "type": 0, "id": 9069864}, {"image_hue": "0x3d6ab3", "title": "\u96ea\u666f\u600e\u4e48\u62cd\u624d\u597d\u770b\uff1f\u5b66\u4f1a\u8fd9\u51e0\u62db\uff0c\u5c31\u7b49\u4e0b\u96ea\u4e86", "url": "https://daily.zhihu.com/story/9069711", "hint": "\u5f20\u5343\u91cc \u00b7 6 \u5206\u949f\u9605\u8bfb", "ga_prefix": "121609", "images": ["http://pic1.zhimg.com/de42da2967b7be32a8f6d0d08da9dee0.jpg"], "multipic": true, "type": 0, "id": 9069711}, {"image_hue": "0x9e8a6f", "title": "\u4e3a\u4ec0\u4e48\u603b\u89c9\u5f97\u4e2d\u56fd\u4eba\u5747\u6536\u5165\u4e0d\u9ad8\uff0c\u7269\u4ef7\u5374\u5f88\u9ad8\uff1f", "url": "https://daily.zhihu.com/story/9069234", "hint": "\u738b\u76f8\u53ca \u00b7 1 \u5206\u949f\u9605\u8bfb", "ga_prefix": "121608", "images": ["http://pic3.zhimg.com/e38102732128a29915d7c3e8d10bd9e2.jpg"], "type": 0, "id": 9069234}, {"image_hue": "0x8d6757", "title": "\u5973\u6027\u771f\u7684\u66f4\u5bb9\u6613\u5f97\u6291\u90c1\u75c7\uff0c\u94b1\u518d\u591a\u4e5f\u4e00\u6837", "url": "https://daily.zhihu.com/story/9061763", "hint": "Han Lu \u00b7 3 \u5206\u949f\u9605\u8bfb", "ga_prefix": "121607", "images": ["http://pic2.zhimg.com/20269ead70f861f356e899537b139499.jpg"], "type": 0, "id": 9061763}, {"image_hue": "0x341410", "title": "\u7269\u7406\u4e2d\u7684\u5404\u79cd\u300c\u573a\u300d\uff0c\u5230\u5e95\u662f\u4ec0\u4e48\uff1f", "url": "https://daily.zhihu.com/story/9069898", "hint": "\u5927\u91ce\u55b5\u6e23 \u00b7 2 \u5206\u949f\u9605\u8bfb", "ga_prefix": "121607", "images": ["http://pic1.zhimg.com/6193b079183d2737acf9683398d694fc.jpg"], "type": 0, "id": 9069898}, {"image_hue": "0xb3744b", "title": "\u770b\u770b\u4eba\u5bb6\u571f\u8033\u5176\uff0c\u6539\u4e86\u4e0b\u7b97\u6cd5\u5c31\u80fd\u8ba9\u4eba\u5747 GDP \u6da8 20%", "url": "https://daily.zhihu.com/story/9068307", "hint": "\u94b1\u7cae\u80e1\u540c \u00b7 1 \u5206\u949f\u9605\u8bfb", "ga_prefix": "121607", "images": ["http://pic1.zhimg.com/df1b9aab1c3c1c19a22243ce2ffdb8c0.jpg"], "type": 0, "id": 9068307}, {"image_hue": "0x23161a", "title": "\u8bfb\u8bfb\u65e5\u62a5 24 \u5c0f\u65f6\u70ed\u95e8 TOP 5 \u00b7 \u5ddd\u666e\u548c\u7845\u8c37\u5927\u4f6c\u4eec\u7684\u300c\u4e92\u8054\u7f51\u5927\u4f1a\u300d", "url": "https://daily.zhihu.com/story/9069631", "hint": "\u7f16\u8f91\u90e8\u5c0f\u674e \u00b7 1 \u5206\u949f\u9605\u8bfb", "ga_prefix": "121607", "images": ["http://pic3.zhimg.com/893952c33d45faeb325cf83d145944de.jpg"], "type": 0, "id": 9069631}, {"image_hue": "0xa1b37d", "title": "\u778e\u626f \u00b7 \u5982\u4f55\u6b63\u786e\u5730\u5410\u69fd", "url": "https://daily.zhihu.com/story/9069850", "hint": "VOL.1250", "ga_prefix": "121606", "images": ["http://pic1.zhimg.com/adcb9f9ee6eb515d7e39a669d81d2640.jpg"], "type": 0, "id": 9069850}]}