{"date": "20191220", "stories": [{"image_hue": "0x465064", "title": "\u4eba\u7c7b\u6709\u54ea\u4e9b\u5927\u79d1\u5b66\u88c5\u7f6e\uff1f\u6211\u56fd\u53c8\u6709\u54ea\u4e9b\uff1f", "url": "https://daily.zhihu.com/story/9718236", "hint": "DZ Gong \u00b7 4 \u5206\u949f\u9605\u8bfb", "ga_prefix": "122020", "images": ["https://pic2.zhimg.com/v2-b55803c827c34f0ecbf83e85f42add1d.jpg"], "type": 0, "id": 9718236}, {"image_hue": "0x755348", "title": "\u5982\u679c\u628a\u5386\u5c4a\u300a\u82f1\u96c4\u8054\u76df\u300b\u5168\u7403\u603b\u51b3\u8d5b\u51a0\u4e9a\u519b\u98a0\u5012\u4f1a\u53d1\u751f\u4ec0\u4e48\uff1f", "url": "https://daily.zhihu.com/story/9718221", "hint": "\u6700\u540e\u7684\u8f7b\u8bed \u00b7 5 \u5206\u949f\u9605\u8bfb", "ga_prefix": "122016", "images": ["https://pic3.zhimg.com/v2-843dff2a0eb11f434954c56482e3fd9a.jpg"], "type": 0, "id": 9718221}, {"image_hue": "0x3b4354", "title": "\u4e3a\u4ec0\u4e48\u79f0\u300a\u661f\u7403\u5927\u6218\u300b\u4e3a\u300c\u592a\u7a7a\u6b4c\u5267\u300d\uff1f", "url": "https://daily.zhihu.com/story/9718211", "hint": "\u5f20\u5c0f\u5317 \u00b7 2 \u5206\u949f\u9605\u8bfb", "ga_prefix": "122009", "images": ["https://pic2.zhimg.com/v2-af9a4004eb57716e0adca824d6836ca5.jpg"], "type": 0, "id": 9718211}, {"image_hue": "0x99a774", "title": "\u6709\u54ea\u4e9b\u8fd0\u52a8\u662f\u8d35\u65cf\u8fd0\u52a8\uff1f", "url": "https://daily.zhihu.com/story/9718227", "hint": "Emma \u00b7 3 \u5206\u949f\u9605\u8bfb", "ga_prefix": "122007", "images": ["https://pic4.zhimg.com/v2-48590e4a975b282f48030ffc1f7bbf0f.jpg"], "type": 0, "id": 9718227}, {"image_hue": "0xa372a3", "title": "\u778e\u626f \u00b7 \u5982\u4f55\u6b63\u786e\u5730\u5410\u69fd", "url": "https://daily.zhihu.com/story/9718249", "hint": "VOL.2287", "ga_prefix": "122006", "images": ["https://pic4.zhimg.com/v2-49420dd6056e29e77b4fa83310f8ebef.jpg"], "type": 0, "id": 9718249}]}