{"date": "20141108", "stories": [{"image_hue": "0x806959", "title": "\u6df1\u591c\u98df\u5802 \u00b7 \u8fdb\u6e05\u534e", "url": "https://daily.zhihu.com/story/4290990", "hint": "\u533f\u540d\u7528\u6237 \u00b7 1 \u5206\u949f\u9605\u8bfb", "ga_prefix": "110822", "images": ["http://pic2.zhimg.com/8f898f84c643c31e0cbcb5b681aa1621.jpg"], "type": 0, "id": 4290990}, {"image_hue": "0x2b1e27", "title": "\u4e70\u65b0\u8f66\uff0c\u56db\u6b65\u5212\u5b9a\u8303\u56f4", "url": "https://daily.zhihu.com/story/4295587", "hint": "\u6b66\u6770 \u00b7 9 \u5206\u949f\u9605\u8bfb", "ga_prefix": "110821", "images": ["http://pic4.zhimg.com/0fb5a633756a3d5058ebd275143ae555.jpg"], "type": 0, "id": 4295587}, {"image_hue": "0xb08d7b", "title": "\u957f\u671f\u6253\u547c\u565c\u8fd9\u4e8b\u6709\u70b9\u4e25\u91cd\uff0c\u5efa\u8bae\u53bb\u533b\u9662\u67e5\u67e5", "url": "https://daily.zhihu.com/story/4295304", "hint": "Ming \u00b7 1 \u5206\u949f\u9605\u8bfb", "ga_prefix": "110820", "images": ["http://pic3.zhimg.com/55122e1299df415a993d8769db95bdf6.jpg"], "type": 0, "id": 4295304}, {"image_hue": "0xad8551", "title": "\u5e74\u4efd\u7684\u79d8\u5bc6\uff1a\u597d\u9152\u662f\u54c1\u51fa\u6765\u7684\u5417\uff1f\uff08\u591a\u56fe\uff09", "url": "https://daily.zhihu.com/story/4249717", "hint": "\u9189\u9e45\u8001\u5e08 \u00b7 6 \u5206\u949f\u9605\u8bfb", "ga_prefix": "110819", "images": ["http://pic2.zhimg.com/a4033e65006a178b92aca63ebbd08862.jpg"], "multipic": true, "type": 0, "id": 4249717}, {"image_hue": "0x73440e", "title": "\u6709\u4eba\u8bf4\u53f0\u6e7e\u7684\u725b\u8089\u9762\u662f\u6e90\u4e8e\u56db\u5ddd\uff0c\u6211\u4eec\u8003\u8bc1\u4e00\u4e0b", "url": "https://daily.zhihu.com/story/4291454", "hint": "\u59da\u5c0f\u9003 \u00b7 2 \u5206\u949f\u9605\u8bfb", "ga_prefix": "110818", "images": ["http://pic4.zhimg.com/fcb3bc0b3491b2177e4d081f868c2d18.jpg"], "type": 0, "id": 4291454}, {"image_hue": "0x392826", "title": "\u4fdd\u517b\u4e0d\u90a3\u4e48\u8d35\u7684\u76ae\u978b\uff0c\u81ea\u5df1\u52a8\u624b\u4e5f\u6709\u4e13\u4e1a\u65b9\u6848", "url": "https://daily.zhihu.com/story/4292924", "hint": "\u5510\u6811\u5f6a \u00b7 2 \u5206\u949f\u9605\u8bfb", "ga_prefix": "110817", "images": ["http://pic2.zhimg.com/ed5997a794abd890381b8a282eb9969f.jpg"], "type": 0, "id": 4292924}, {"image_hue": "0xb09172", "title": "\u5982\u679c\u4f60\u5de7\u514b\u529b\u53ea\u77e5\u9053\u8d39\u5217\u7f57\u2026\u2026\u4f60\u9700\u8981\u8fd9\u7bc7\uff08\u591a\u56fe\uff09", "url": "https://daily.zhihu.com/story/4284656", "hint": "\u70b9\u68c0\u5f62\u9ab8 \u00b7 1 \u5206\u949f\u9605\u8bfb", "ga_prefix": "110816", "images": ["http://pic3.zhimg.com/9bcea4bbf756615f1e6e8a883b20154c.jpg"], "multipic": true, "type": 0, "id": 4284656}, {"image_hue": "0xb39e7d", "title": "\u4e66\u8bfb\u5f97\u5c11\u4e0d\u6253\u7d27\uff0c\u7ecf\u5178\u8bfb\u5f97\u5c11\u5c31\u4e0d\u592a\u597d\u4e86", "url": "https://daily.zhihu.com/story/4285938", "hint": "\u85e5\u5e2b \u00b7 7 \u5206\u949f\u9605\u8bfb", "ga_prefix": "110815", "images": ["http://pic2.zhimg.com/5534e6b8eefdfcdf9390533f73d34621.jpg"], "type": 0, "id": 4285938}, {"image_hue": "0x4b4b4b", "title": "\u62ff\u7834\u4ed1\u7684\u300c\u77ee\u300d\uff0c\u5f88\u5927\u7a0b\u5ea6\u4e0a\u662f\u79cd\u9519\u89c9", "url": "https://daily.zhihu.com/story/4285856", "hint": "jo jo \u00b7 1 \u5206\u949f\u9605\u8bfb", "ga_prefix": "110814", "images": ["http://pic1.zhimg.com/4477b4cf1d72e0c84766bb88f713fc3d.jpg"], "type": 0, "id": 4285856}, {"image_hue": "0xb39b7d", "title": "\u4e8c\u6218\u65f6\u7684\u82f1\u56fd\uff0c\u7528\u4e09\u5206\u4e4b\u4e00\u7cae\u98df\u517b\u6d3b\u4e86\u6240\u6709\u4eba\uff08\u591a\u56fe\uff09", "url": "https://daily.zhihu.com/story/4294553", "hint": "\u7fc1\u6615 \u00b7 5 \u5206\u949f\u9605\u8bfb", "ga_prefix": "110813", "images": ["http://pic2.zhimg.com/411265e65937316ddfff9f008a58b25e.jpg"], "multipic": true, "type": 0, "id": 4294553}, {"image_hue": "0x8ab37d", "title": "\u540d\u53eb\u7535\u78c1\u8f90\u5c04\u633a\u5413\u4eba\uff0c\u5b9e\u9645\u4e0a\u5927\u90e8\u5206\u4eba\u755c\u65e0\u5bb3", "url": "https://daily.zhihu.com/story/4294915", "hint": "\u77e5\u4e4e\u7528\u6237 \u00b7 2 \u5206\u949f\u9605\u8bfb", "ga_prefix": "110812", "images": ["http://pic4.zhimg.com/0774775cfc890f971386622da510f753.jpg"], "type": 0, "id": 4294915}, {"image_hue": "0x5f5f5f", "title": "\u4e0d\u662f\u8d85\u80fd\u529b\uff1a\u95ed\u773c\u4e5f\u80fd\u611f\u53d7\u5230\u6709\u4eba\u6307\u7740\u81ea\u5df1\u7684\u989d\u5934", "url": "https://daily.zhihu.com/story/4268052", "hint": "\u8d75\u601d\u5bb6 \u00b7 1 \u5206\u949f\u9605\u8bfb", "ga_prefix": "110811", "images": ["http://pic4.zhimg.com/3d332435340b52ad3bec04da5e40afa2.jpg"], "type": 0, "id": 4268052}, {"image_hue": "0x7db38c", "title": "\u7259\u9f7f\u77eb\u6b63\u662f\u4ef6\u5927\u597d\u4e8b\uff0c\u8d81\u5e74\u8f7b\u5feb\u70b9\u4e0b\u51b3\u5fc3\u505a\u5427", "url": "https://daily.zhihu.com/story/4284281", "hint": "\u9ad8\u9e92 \u00b7 1 \u5206\u949f\u9605\u8bfb", "ga_prefix": "110810", "images": ["http://pic1.zhimg.com/fbebec23ac16c0a73cab98528c775e4c.jpg"], "type": 0, "id": 4284281}, {"image_hue": "0x3d2b2e", "title": "20 \u5e74\u524d\u7684\u4e00\u573a\u6f14\u5531\u4f1a\uff0c\u53ef\u80fd\u662f\u4e2d\u56fd\u6447\u6eda\u53f2\u6700\u75af\u72c2\u7684\u4e00\u591c\uff08\u591a\u56fe\uff09", "url": "https://daily.zhihu.com/story/4294082", "hint": "\u5468\u5317\u6811 \u00b7 8 \u5206\u949f\u9605\u8bfb", "ga_prefix": "110809", "images": ["http://pic3.zhimg.com/da1a701a172948d1285710c23725c203.jpg"], "multipic": true, "type": 0, "id": 4294082}, {"image_hue": "0x9e78ab", "title": "\u300c\u4e00\u8033\u5149\u628a\u4eba\u6247\u9192\u4e86\u300d\uff0c\u6709\u4f9d\u636e\u4e48\uff1f", "url": "https://daily.zhihu.com/story/4284397", "hint": "\u6768\u9492 \u00b7 1 \u5206\u949f\u9605\u8bfb", "ga_prefix": "110808", "images": ["http://pic3.zhimg.com/abe9c71762e7aa6b2407cd4f0376d7b8.jpg"], "type": 0, "id": 4284397}, {"image_hue": "0x786254", "title": "\u4e3a\u4e86\u5065\u5eb7\uff0c\u4e00\u5929\u5403\u51e0\u4e2a\u9e21\u86cb\u6bd4\u8f83\u597d\uff1f", "url": "https://daily.zhihu.com/story/4291152", "hint": "\u5e84\u65f6\u5229\u548c \u00b7 3 \u5206\u949f\u9605\u8bfb", "ga_prefix": "110807", "images": ["http://pic4.zhimg.com/6700ad86e520dfb3a312ad491968e628.jpg"], "type": 0, "id": 4291152}, {"image_hue": "0x7da2b3", "title": "\u300a\u9ed1\u6697\u9a91\u58eb\u300b\uff1a\u80cc\u8d1f\u539f\u7f6a\u7684\u6b63\u4e49 \u00b7 \u767b\u5cf0\u9020\u6781\u7684\u90aa\u6076", "url": "https://daily.zhihu.com/story/4291375", "hint": "\u9b4f\u77e5\u8d85 \u00b7 5 \u5206\u949f\u9605\u8bfb", "ga_prefix": "110807", "images": ["http://pic3.zhimg.com/cab498b66468844b6be992e6e226d6e8.jpg"], "type": 0, "id": 4291375}, {"image_hue": "0xb3a27d", "title": "\u6709\u54ea\u4e9b 100 \u5143\u4ee5\u4e0b\u7684\u597d\u4e1c\u897f\u503c\u5f97\u4e70\uff1f\uff08\u591a\u56fe\uff09", "url": "https://daily.zhihu.com/story/4291823", "hint": "\u826f\u4f11 \u00b7 6 \u5206\u949f\u9605\u8bfb", "ga_prefix": "110807", "images": ["http://pic1.zhimg.com/3f0dace7e58ac8b53fa720b0556fb8bd.jpg"], "multipic": true, "type": 0, "id": 4291823}, {"image_hue": "0x987db3", "title": "\u778e\u626f \u00b7 \u5982\u4f55\u6b63\u786e\u5730\u5410\u69fd", "url": "https://daily.zhihu.com/story/4294795", "hint": "VOL.483", "ga_prefix": "110806", "images": ["http://pic4.zhimg.com/d6995f2668dd02be19252c4966f15f52.jpg"], "type": 0, "id": 4294795}]}