{"date": "20161029", "stories": [{"image_hue": "0xb38f66", "title": "\u5c0f\u4e8b \u00b7 \u65e0\u6cd5\u9a7e\u9a6d\u8377\u5c14\u8499", "url": "https://daily.zhihu.com/story/8928039", "hint": "VOL.150", "ga_prefix": "102922", "images": ["http://pic1.zhimg.com/c32366ce4d6e3416e8e25f65c5b6c934.jpg"], "type": 0, "id": 8928039}, {"image_hue": "0x8fb37d", "title": "\u4e24\u4e2a\u6027\u683c\u8fe5\u5f02\u7684\u4eba\uff0c\u5982\u4f55\u505a\u592b\u59bb\uff1f", "url": "https://daily.zhihu.com/story/8913851", "hint": "\u738bRRR \u00b7 2 \u5206\u949f\u9605\u8bfb", "ga_prefix": "102921", "images": ["http://pic1.zhimg.com/9379ff3c07172e8697b82357156228fc.jpg"], "type": 0, "id": 8913851}, {"image_hue": "0xb37d85", "title": "\u8ba1\u7b97\u673a\u89c6\u89c9\u8fdb\u5165\u74f6\u9888\u4e86\uff1f\u8fd8\u5927\u6709\u641e\u5934\u5462", "url": "https://daily.zhihu.com/story/8915582", "hint": "\u5468\u535a\u78ca \u00b7 4 \u5206\u949f\u9605\u8bfb", "ga_prefix": "102920", "images": ["http://pic4.zhimg.com/05c29e31c8c0529ca074d9e5ce9a1d67.jpg"], "type": 0, "id": 8915582}, {"image_hue": "0x172537", "title": "\u60f3\u901a\u8fc7\u71ac\u591c\u6210\u4e3a\u4eba\u751f\u8d62\u5bb6\uff1f\u4f60\u53ef\u80fd\u9700\u8981\u5148\u77e5\u9053\u8fd9\u4e9b", "url": "https://daily.zhihu.com/story/8918407", "hint": "\u7aa6\u6cfd\u5357 \u00b7 13 \u5206\u949f\u9605\u8bfb", "ga_prefix": "102919", "images": ["http://pic3.zhimg.com/d3a993366d94f6b964f8a08c0a75fe0e.jpg"], "type": 0, "id": 8918407}, {"image_hue": "0x101217", "title": "\u5b87\u5b99\u771f\u7684\u8ddf\u6c14\u7403\u4e00\u6837\u5728\u81a8\u80c0\u53d8\u5927\u5417\uff1f", "url": "https://daily.zhihu.com/story/8914193", "hint": "\u72d0\u72f8\u5148\u751f \u00b7 7 \u5206\u949f\u9605\u8bfb", "ga_prefix": "102918", "images": ["http://pic4.zhimg.com/9b6f6ba6c78a8caff6f68aa5ea86102f.jpg"], "type": 0, "id": 8914193}, {"image_hue": "0xad9279", "title": "\u77e5\u4e4e\u597d\u95ee\u9898 \u00b7 \u5496\u5561\u548c\u9152\u53ef\u4ee5\u5982\u4f55\u642d\u914d\uff1f", "url": "https://daily.zhihu.com/story/8931014", "hint": " \u00b7 1 \u5206\u949f\u9605\u8bfb", "ga_prefix": "102917", "images": ["http://pic1.zhimg.com/a4715555c7a8729bd4c77e9e893c13b0.jpg"], "type": 0, "id": 8931014}, {"image_hue": "0x171b40", "title": "\u4e3a\u4ec0\u4e48\u5feb\u4e50\u7684\u65f6\u5149\u603b\u662f\u8fc7\u5f97\u7279\u522b\u5feb\uff1f", "url": "https://daily.zhihu.com/story/8929814", "hint": "\u5f20\u6615 \u00b7 2 \u5206\u949f\u9605\u8bfb", "ga_prefix": "102916", "images": ["http://pic2.zhimg.com/9a0e3ad358f8dda9206d96f77f10dd7d.jpg"], "type": 0, "id": 8929814}, {"image_hue": "0x484e2c", "title": "\u4e3a\u4ec0\u4e48\u8003\u4e0a 985 \u8ba9\u6211\u4eec\u300c\u4e00\u65e0\u6240\u6709\u300d", "url": "https://daily.zhihu.com/story/8930844", "hint": "\u718a\u5e0c\u7075 \u00b7 3 \u5206\u949f\u9605\u8bfb", "ga_prefix": "102915", "images": ["http://pic3.zhimg.com/d311aa984ea4f361857f0ef9befbf6a2.jpg"], "type": 0, "id": 8930844}, {"image_hue": "0x4f4337", "title": "\u4e2d\u56fd\u533b\u751f\u7684\u5de5\u8d44\u6709\u591a\u4f4e\uff0c\u6765\u8ba4\u771f\u7b97\u4e00\u7b97", "url": "https://daily.zhihu.com/story/8928932", "hint": "\u6e29\u4e49\u98de \u00b7 2 \u5206\u949f\u9605\u8bfb", "ga_prefix": "102914", "images": ["http://pic3.zhimg.com/33b7f0af13ce5ea77774de08e1eb2382.jpg"], "type": 0, "id": 8928932}, {"image_hue": "0x7f3e2c", "title": "\u6311\u9009\u597d\u559d\u7684\u8089\u6842\uff0c\u5149\u95fb\u9999\u53ef\u4e0d\u7ba1\u7528", "url": "https://daily.zhihu.com/story/8924683", "hint": "\u8c22\u4f1f\u6587 \u00b7 2 \u5206\u949f\u9605\u8bfb", "ga_prefix": "102913", "images": ["http://pic2.zhimg.com/796a43e5abd8c81a5872776c93886f0d.jpg"], "type": 0, "id": 8924683}, {"image_hue": "0xb3b3b3", "title": "\u5927\u8bef \u00b7 \u7537\u751f\uff0c\u6709\u4e2a\u5973\u751f\u540d\u5b57", "url": "https://daily.zhihu.com/story/8918567", "hint": "\u5de6\u624b\u4e4b\u5f71 \u00b7 2 \u5206\u949f\u9605\u8bfb", "ga_prefix": "102912", "images": ["http://pic2.zhimg.com/6dc8c71e01dac8add33cceb9052c3d7d.jpg"], "type": 0, "id": 8918567}, {"image_hue": "0x2d1b20", "title": "\u9b54\u5ca9\u4e09\u6770\u4e4b\u524d\uff0c\u4f60\u4e0d\u77e5\u9053\u7684\u4e2d\u56fd\u6447\u6eda\u7f16\u5e74\u53f2", "url": "https://daily.zhihu.com/story/8915348", "hint": "\u4e2d\u6563 \u00b7 11 \u5206\u949f\u9605\u8bfb", "ga_prefix": "102911", "images": ["http://pic3.zhimg.com/86a6169f578d9aeb41aca203aa36a3c6.jpg"], "type": 0, "id": 8915348}, {"image_hue": "0x7d98b3", "title": "\u522b\u518d\u6302\u300a\u4e07\u9a6c\u5954\u817e\u300b\u4e86\uff0c\u5ba2\u5385\u88c5\u9970\u753b\u53ef\u4ee5\u66f4\u6709\u98ce\u683c", "url": "https://daily.zhihu.com/story/8913474", "hint": "\u65ee\u65ef \u00b7 4 \u5206\u949f\u9605\u8bfb", "ga_prefix": "102910", "images": ["http://pic3.zhimg.com/8a4b623a9c7c665d62e220fa4ffa3dda.jpg"], "type": 0, "id": 8913474}, {"image_hue": "0xb3927d", "title": "\u5f53\u6f14\u5458\u8981\u8bfb\u54ea\u4e9b\u4e66\uff1f\u542c\u542c\u4f5c\u4e3a\u91d1\u9a6c\u5956\u8bc4\u5ba1\u7684\u5979\u600e\u4e48\u8bf4", "url": "https://daily.zhihu.com/story/8922111", "hint": "\u90ce\u7956\u7b60 \u00b7 2 \u5206\u949f\u9605\u8bfb", "ga_prefix": "102909", "images": ["http://pic2.zhimg.com/a745c2fb10e7fe42f847edd2d84740f5.jpg"], "type": 0, "id": 8922111}, {"image_hue": "0x21171a", "title": "\u660e\u77e5\u9053\u5206\u624b\u5c31\u8be5\u653e\u4e0b\uff0c\u5374\u5b66\u4e0d\u4f1a\u91ca\u6000\u53ef\u600e\u4e48\u529e\uff1f", "url": "https://daily.zhihu.com/story/8918160", "hint": "KnowYourself \u00b7 9 \u5206\u949f\u9605\u8bfb", "ga_prefix": "102908", "images": ["http://pic1.zhimg.com/ad51a79d505c397dfb79e73150713ec8.jpg"], "type": 0, "id": 8918160}, {"image_hue": "0xb3a27d", "title": "\u8bc6\u522b\u4e00\u79d2\u949f\uff0c\u7ebf\u4e0b\u5341\u5e74\u529f\uff1a\u8bed\u97f3\u8f93\u5165\u5982\u4f55\u4e00\u5206\u949f 400 \u5b57", "url": "https://daily.zhihu.com/story/8927797", "hint": "\u79d1\u5927\u8baf\u98de \u00b7 5 \u5206\u949f\u9605\u8bfb", "ga_prefix": "102907", "images": ["http://pic4.zhimg.com/f9daa2d8d36c560432381c3aa35be763.jpg"], "type": 0, "id": 8927797}, {"image_hue": "0xa87f53", "title": "\u4e3a\u4e86\u51cf\u538b\u73a9\u6e38\u620f\uff0c\u4e0a\u763e\u4e4b\u540e\u538b\u529b\u66f4\u5927\u4e86", "url": "https://daily.zhihu.com/story/8919238", "hint": "\u8d75\u601d\u5bb6 \u00b7 8 \u5206\u949f\u9605\u8bfb", "ga_prefix": "102907", "images": ["http://pic2.zhimg.com/ad290c8bfff3ca06172c2a006da1b519.jpg"], "type": 0, "id": 8919238}, {"image_hue": "0x2e3842", "title": "\u300c\u9760\u53f3\u8d70\u300d\u8fd9\u79cd\u7b80\u5355\u5236\u5ea6\uff0c\u4e5f\u85cf\u7740\u6df1\u523b\u7684\u7ecf\u6d4e\u5b66\u539f\u7406", "url": "https://daily.zhihu.com/story/8918380", "hint": "Richard Xu \u00b7 5 \u5206\u949f\u9605\u8bfb", "ga_prefix": "102907", "images": ["http://pic1.zhimg.com/0fed9361a3323d4eb986bd0fe3544b40.jpg"], "type": 0, "id": 8918380}, {"image_hue": "0x749850", "title": "\u8bfb\u8bfb\u65e5\u62a5 24 \u5c0f\u65f6\u70ed\u95e8 TOP 5 \u00b7 \u6e38\u620f\u4e2d\u7684\u5341\u5927\u672a\u77e5\u751f\u7269", "url": "https://daily.zhihu.com/story/8929615", "hint": "\u7f16\u8f91\u90e8\u5c0f\u674e \u00b7 1 \u5206\u949f\u9605\u8bfb", "ga_prefix": "102907", "images": ["http://pic3.zhimg.com/7a3ff69ebc076a7262bf7e8ded82c74e.jpg"], "type": 0, "id": 8929615}, {"image_hue": "0x7d92b3", "title": "\u778e\u626f \u00b7 \u5982\u4f55\u6b63\u786e\u5730\u5410\u69fd", "url": "https://daily.zhihu.com/story/8927492", "hint": "VOL.1202", "ga_prefix": "102906", "images": ["http://pic4.zhimg.com/177b8778f7d8a52688265043fae62ed3.jpg"], "type": 0, "id": 8927492}]}