{"date": "20200705", "stories": [{"image_hue": "0x423a2e", "title": "\u5c0f\u4e8b \u00b7 \u732b\u88ab\u5173\u4e86\u4e24\u4e2a\u6708\u4e4b\u540e", "url": "https://daily.zhihu.com/story/9725588", "hint": "VOL.1209", "ga_prefix": "070507", "images": ["https://pic2.zhimg.com/v2-b20d8f7911395f7a272fa0cf2f91e021.jpg"], "type": 0, "id": 9725588}, {"image_hue": "0x3e2b28", "title": "\u5982\u4f55\u4ece\u793e\u4f1a\u5fc3\u7406\u5b66\u89d2\u5ea6\u5206\u6790\u996d\u5708\u6587\u5316?", "url": "https://daily.zhihu.com/story/9725571", "hint": "\u65f6\u60a6Shadow \u00b7 3 \u5206\u949f\u9605\u8bfb", "ga_prefix": "070507", "images": ["https://pic3.zhimg.com/v2-7f7109ab003927293e26e0bb60b8dc7e.jpg"], "type": 0, "id": 9725571}, {"image_hue": "0x064f5a", "title": "\u5929\u6587\u5b66\u5bb6\u770b\u5230\u6781\u5149\u65f6\u7684\u611f\u53d7\u548c\u666e\u901a\u4eba\u6709\u4ec0\u4e48\u4e0d\u4e00\u6837\uff1f", "url": "https://daily.zhihu.com/story/9725594", "hint": "\u72d0\u72f8\u5148\u751f \u00b7 3 \u5206\u949f\u9605\u8bfb", "ga_prefix": "070507", "images": ["https://pic3.zhimg.com/v2-3aa4fea4b3b1af9b18b25ed0965f022e.jpg"], "type": 0, "id": 9725594}, {"image_hue": "0x344a39", "title": "\u6709\u6ca1\u6709\u94c1\u8def\u50cf\u6e38\u4e50\u573a\u4e00\u6837\u87ba\u65cb\u4e0a\u5347\uff1f", "url": "https://daily.zhihu.com/story/9725587", "hint": "\u77e5\u4e4e\u7528\u6237 \u00b7 1 \u5206\u949f\u9605\u8bfb", "ga_prefix": "070507", "images": ["https://pic3.zhimg.com/v2-7aa72216366cab1bae9eb1ae26846d5e.jpg"], "type": 0, "id": 9725587}, {"image_hue": "0xb37d9f", "title": "\u4e3a\u4ec0\u4e48\u53f2\u9ad8\u6cbb\u548c\u5510\u8001\u9e2d\u662f\u8205\u7525\u5173\u7cfb\uff1f", "url": "https://daily.zhihu.com/story/9725610", "hint": "\u75af\u766b\u7684A\u5175\u8005 \u00b7 3 \u5206\u949f\u9605\u8bfb", "ga_prefix": "070507", "images": ["https://pic4.zhimg.com/v2-944885bce1ba42f87139728b60e9c633.jpg"], "multipic": true, "type": 0, "id": 9725610}, {"image_hue": "0xb3a47d", "title": "\u5927\u8bef \u00b7 \u5f53\u65e0\u795e\u8bba\u8005\u89c1\u5230\u9b3c", "url": "https://daily.zhihu.com/story/9725580", "hint": "\u738b\u5b50\u541b \u00b7 1 \u5206\u949f\u9605\u8bfb", "ga_prefix": "070507", "images": ["https://pic2.zhimg.com/v2-81ad16a6621e258ba5142bd6e3c7a449.jpg"], "type": 0, "id": 9725580}]}